{"assets":{"F1606019E2FC33A158CFAB6CB02DEEE4":{"type":"texture","index":1,"assetRequest":{"type":"slide","state":"contents","slide":"none"},"url":{"native":"assets\/487370F2-3334-4CF0-BAF7-112419BCF6D3.pdf"},"width":1349,"height":65},"694D88DB94A5EC859458CE1652F311A8":{"type":"texture","index":8,"assetRequest":{"type":"slide","state":"contents","slide":"none"},"url":{"native":"assets\/487370F2-3334-4CF0-BAF7-112419BCF6D3.pdf"},"width":1920,"height":1080},"467950B8C34586EDD279AE172F705699":{"type":"texture","index":3,"assetRequest":{"type":"slide","state":"contents","slide":"none"},"url":{"native":"assets\/487370F2-3334-4CF0-BAF7-112419BCF6D3.pdf"},"width":401,"height":55},"12B92BA02378E659CCFC9EBD056CFFC8":{"type":"texture","index":6,"assetRequest":{"type":"slide","state":"contents","slide":"none"},"url":{"native":"assets\/487370F2-3334-4CF0-BAF7-112419BCF6D3.pdf"},"width":609,"height":419},"C25C25FF361FB24FC35F6B120D2F252D":{"type":"texture","index":0,"assetRequest":{"type":"slide","state":"contents","slide":"none"},"url":{"native":"assets\/487370F2-3334-4CF0-BAF7-112419BCF6D3.pdf"},"width":1920,"height":1080},"594B7529A2D3B69A346AC2757CB9EC71":{"type":"texture","index":9,"assetRequest":{"type":"slide","state":"contents","slide":"none"},"url":{"native":"assets\/487370F2-3334-4CF0-BAF7-112419BCF6D3.pdf"},"width":1920,"height":1080},"234DC0114C5052C599F20172FEC4564C":{"type":"texture","index":5,"assetRequest":{"type":"slide","state":"contents","slide":"none"},"url":{"native":"assets\/487370F2-3334-4CF0-BAF7-112419BCF6D3.pdf"},"width":1119,"height":107},"88DA894CD5271F0FBBEEE8AF7E1ED0DA":{"type":"texture","index":7,"assetRequest":{"type":"slide","state":"contents","slide":"none"},"url":{"native":"assets\/487370F2-3334-4CF0-BAF7-112419BCF6D3.pdf"},"width":1739,"height":247},"1FF09739281378389A7864A2FABF1646":{"type":"texture","index":4,"assetRequest":{"type":"slide","state":"contents","slide":"none"},"url":{"native":"assets\/487370F2-3334-4CF0-BAF7-112419BCF6D3.pdf"},"width":600,"height":125},"C398C6CBE44576E26EDBCA30676F307F":{"type":"texture","index":2,"assetRequest":{"type":"slide","state":"contents","slide":"none"},"url":{"native":"assets\/487370F2-3334-4CF0-BAF7-112419BCF6D3.pdf"},"width":23,"height":17}},"events":[{"effects":[{"beginTime":0,"baseLayer":{"animations":[],"initialState":{"affineTransform":[1,0,0,1,0,0],"masksToBounds":false,"rotation":0,"scale":1,"position":{"pointX":708.42601013183594,"pointY":556.29769897460938},"width":1119,"sublayerTransform":[1,0,0,0,0,1,0,0,0,0,1,0,0,0,0,1],"contentsRect":{"y":0,"x":0,"width":1,"height":1},"opacity":1,"edgeAntialiasingMask":251658240,"height":107,"hidden":false,"anchorPoint":{"pointX":0.5,"pointY":0.5}},"objectID":"08632DD1-A4B9-417E-9ACE-10EFF3882177","layers":[{"animations":[],"initialState":{"affineTransform":[1,0,0,1,0,0],"masksToBounds":false,"rotation":0,"scale":1,"position":{"pointX":811.07398986816406,"pointY":37.202301025390625},"width":1119,"sublayerTransform":[1,0,0,0,0,1,0,0,0,0,1,-0.00035007912466775983,0,0,0,1],"contentsRect":{"y":0,"x":0,"width":1,"height":1},"opacity":1,"edgeAntialiasingMask":251658240,"height":107,"hidden":false,"anchorPoint":{"pointX":0.7248203662807543,"pointY":0.34768505631206192}},"layers":[{"animations":[{"additive":false,"timeOffset":0,"beginTime":1e-100,"repeatCount":0,"fillMode":"both","duration":0.01,"autoreverses":false,"animations":[{"additive":false,"timeOffset":0,"beginTime":0,"from":{"scalar":true},"repeatCount":0,"fillMode":"both","duration":0.0001,"autoreverses":false,"property":"hidden","to":{"scalar":false},"removedOnCompletion":true},{"additive":false,"timeOffset":0,"beginTime":0.0001,"from":{"scalar":false},"repeatCount":0,"fillMode":"forwards","duration":0.0099000000000000008,"autoreverses":false,"property":"hidden","to":{"scalar":false},"removedOnCompletion":true}],"removedOnCompletion":false}],"layers":[],"texturedRectangle":{"isBackgroundTexture":true,"singleTextureOpacity":1,"textureType":5,"textBaseline":0,"textXHeight":0,"isVerticalText":false},"initialState":{"affineTransform":[1,0,0,1,0,0],"masksToBounds":false,"rotation":0,"scale":1,"position":{"pointX":546.57398986816406,"pointY":40.702301025390625},"width":1119,"sublayerTransform":[1,0,0,0,0,1,0,0,0,0,1,0,0,0,0,1],"contentsRect":{"y":0,"x":0,"width":1,"height":1},"opacity":1,"edgeAntialiasingMask":0,"height":107,"hidden":true,"anchorPoint":{"pointX":0.5,"pointY":0.5}},"texture":"234DC0114C5052C599F20172FEC4564C"}]}]},"effects":[],"duration":0.01,"type":"buildIn","attributes":{"direction":0},"name":"apple:appear","objectID":"08632DD1-A4B9-417E-9ACE-10EFF3882177"}],"automaticPlay":false,"hyperlinks":[],"accessibility":[{"text":"Computing P(x)","targetRectangle":{"y":190.44745779037476,"x":98.599999904632568,"width":403.2600000000001,"height":66.404617309570312}},{"text":"pasted-image.pdf","targetRectangle":{"y":359.92463073134422,"x":1372.4314422607422,"width":484.055419921875,"height":415.23040771484375}},{"text":"The direct way:","targetRectangle":{"y":506.79770004749298,"x":152.92601013183594,"width":399.29999999999995,"height":66.404617309570312}},{"text":"output","targetRectangle":{"y":953.3394775390625,"x":1241.7630462646484,"width":113.45100000000002,"height":44.908004760742301}},{"text":"pasted-image.pdf","targetRectangle":{"y":298.54428100585938,"x":661.4075927734375,"width":597.18487548828125,"height":122.41463470458984}},{"text":"Model-based Information Estimate","targetRectangle":{"y":89,"x":99,"width":1352.0950012159346,"height":100.53440856933594}},{"text":"output","targetRectangle":{"y":685.27264404296864,"x":1261.1632080078125,"width":113.45100000000002,"height":44.908004760742301}},{"text":"pasted-image.pdf","targetRectangle":{"y":521.5151424407959,"x":661.40751647949219,"width":592.26043701171875,"height":73.604621887207031}},{"text":"inputs","targetRectangle":{"y":819.30609512329102,"x":1241.7630462646484,"width":106.9380000000001,"height":44.908004760742301}},{"text":"inputs","targetRectangle":{"y":456.60183306884767,"x":1319.3929481506348,"width":44.908004760742188,"height":106.93799999999999}},{"text":"￼","targetRectangle":{"y":1033.9999701976776,"x":949.49999516521348,"width":20.015999999999963,"height":21.496002197265625}},{"text":"Sampling segment by segment:","targetRectangle":{"y":877.06872665882111,"x":152.92601013183594,"width":826.86999999999989,"height":66.404617309570312}},{"text":"pasted-image.pdf","targetRectangle":{"y":806.94476318359375,"x":1373.2510833740234,"width":500.37890625,"height":243.20823669433594}}],"baseLayer":{"animations":[],"initialState":{"affineTransform":[1,0,0,1,0,0],"masksToBounds":false,"rotation":0,"scale":1,"position":{"pointX":960,"pointY":540},"width":1920,"sublayerTransform":[1,0,0,0,0,1,0,0,0,0,1,0,0,0,0,1],"contentsRect":{"y":0,"x":0,"width":1,"height":1},"opacity":1,"edgeAntialiasingMask":251658240,"height":1080,"hidden":false,"anchorPoint":{"pointX":0.5,"pointY":0.5}},"layers":[{"animations":[],"initialState":{"affineTransform":[1,0,0,1,0,0],"masksToBounds":false,"rotation":0,"scale":1,"position":{"pointX":960,"pointY":540},"width":1920,"sublayerTransform":[1,0,0,0,0,1,0,0,0,0,1,0,0,0,0,1],"contentsRect":{"y":0,"x":0,"width":1,"height":1},"opacity":1,"edgeAntialiasingMask":251658240,"height":1080,"hidden":false,"anchorPoint":{"pointX":0.5,"pointY":0.5}},"layers":[{"animations":[],"initialState":{"affineTransform":[1,0,0,1,0,0],"masksToBounds":false,"rotation":0,"scale":1,"position":{"pointX":960,"pointY":540},"width":1920,"sublayerTransform":[1,0,0,0,0,1,0,0,0,0,1,0,0,0,0,1],"contentsRect":{"y":0,"x":0,"width":1,"height":1},"opacity":1,"edgeAntialiasingMask":251658240,"height":1080,"hidden":false,"anchorPoint":{"pointX":0.5,"pointY":0.5}},"layers":[{"animations":[],"layers":[],"texturedRectangle":{"isBackgroundTexture":true,"singleTextureOpacity":1,"textureType":1,"textBaseline":0,"textXHeight":0,"isVerticalText":false},"initialState":{"affineTransform":[1,0,0,1,0,0],"masksToBounds":false,"rotation":0,"scale":1,"position":{"pointX":960,"pointY":540},"width":1920,"sublayerTransform":[1,0,0,0,0,1,0,0,0,0,1,0,0,0,0,1],"contentsRect":{"y":0,"x":0,"width":1,"height":1},"opacity":1,"edgeAntialiasingMask":0,"height":1080,"hidden":false,"anchorPoint":{"pointX":0.5,"pointY":0.5}},"texture":"C25C25FF361FB24FC35F6B120D2F252D"}]}]},{"animations":[],"initialState":{"affineTransform":[1,0,0,1,0,0],"masksToBounds":false,"rotation":0,"scale":1,"position":{"pointX":960,"pointY":540},"width":1920,"sublayerTransform":[1,0,0,0,0,1,0,0,0,0,1,0,0,0,0,1],"contentsRect":{"y":0,"x":0,"width":1,"height":1},"opacity":1,"edgeAntialiasingMask":251658240,"height":1080,"hidden":false,"anchorPoint":{"pointX":0.5,"pointY":0.5}},"layers":[{"animations":[],"initialState":{"affineTransform":[1,0,0,1,0,0],"masksToBounds":false,"rotation":0,"scale":1,"position":{"pointX":769.5,"pointY":117.49999999999997},"width":1349,"sublayerTransform":[1,0,0,0,0,1,0,0,0,0,1,0,0,0,0,1],"contentsRect":{"y":0,"x":0,"width":1,"height":1},"opacity":1,"edgeAntialiasingMask":251658240,"height":65,"hidden":false,"anchorPoint":{"pointX":0.5,"pointY":0.5}},"layers":[{"animations":[],"layers":[],"texturedRectangle":{"singleTextureOpacity":1,"textXHeight":0.67607692307692313,"textBaseline":0.9552278958834135,"isBackgroundTexture":true,"isVerticalText":false,"textColor":[0,0,0,1],"textureType":6},"initialState":{"affineTransform":[1,0,0,1,0,0],"masksToBounds":false,"rotation":0,"scale":1,"position":{"pointX":682.5,"pointY":56.500000000000028},"width":1349,"sublayerTransform":[1,0,0,0,0,1,0,0,0,0,1,0,0,0,0,1],"contentsRect":{"y":0,"x":0,"width":1,"height":1},"opacity":1,"edgeAntialiasingMask":0,"height":65,"hidden":false,"anchorPoint":{"pointX":0.5,"pointY":0.5}},"texture":"F1606019E2FC33A158CFAB6CB02DEEE4"}]}]},{"animations":[],"initialState":{"affineTransform":[1,0,0,1,0,0],"masksToBounds":false,"rotation":0,"scale":1,"position":{"pointX":960,"pointY":540},"width":1920,"sublayerTransform":[1,0,0,0,0,1,0,0,0,0,1,0,0,0,0,1],"contentsRect":{"y":0,"x":0,"width":1,"height":1},"opacity":1,"edgeAntialiasingMask":251658240,"height":1080,"hidden":false,"anchorPoint":{"pointX":0.5,"pointY":0.5}},"layers":[{"animations":[],"initialState":{"affineTransform":[1,0,0,1,0,0],"masksToBounds":false,"rotation":0,"scale":1,"position":{"pointX":956.49999516521348,"pointY":1038.4999701976776},"width":23,"sublayerTransform":[1,0,0,0,0,1,0,0,0,0,1,0,0,0,0,1],"contentsRect":{"y":0,"x":0,"width":1,"height":1},"opacity":1,"edgeAntialiasingMask":251658240,"height":17,"hidden":false,"anchorPoint":{"pointX":0.5,"pointY":0.5}},"layers":[{"animations":[],"layers":[],"texturedRectangle":{"singleTextureOpacity":1,"textXHeight":0.54741176470588226,"textBaseline":0.92129520808949195,"isBackgroundTexture":true,"isVerticalText":false,"textColor":[0,0,0,1],"textureType":6},"initialState":{"affineTransform":[1,0,0,1,0,0],"masksToBounds":false,"rotation":0,"scale":1,"position":{"pointX":13.500004834786523,"pointY":14.500029802322388},"width":23,"sublayerTransform":[1,0,0,0,0,1,0,0,0,0,1,0,0,0,0,1],"contentsRect":{"y":0,"x":0,"width":1,"height":1},"opacity":1,"edgeAntialiasingMask":0,"height":17,"hidden":false,"anchorPoint":{"pointX":0.5,"pointY":0.5}},"texture":"C398C6CBE44576E26EDBCA30676F307F"}]}]},{"animations":[],"initialState":{"affineTransform":[1,0,0,1,0,0],"masksToBounds":false,"rotation":0,"scale":1,"position":{"pointX":960,"pointY":540},"width":1920,"sublayerTransform":[1,0,0,0,0,1,0,0,0,0,1,0,0,0,0,1],"contentsRect":{"y":0,"x":0,"width":1,"height":1},"opacity":1,"edgeAntialiasingMask":251658240,"height":1080,"hidden":false,"anchorPoint":{"pointX":0.5,"pointY":0.5}},"layers":[{"animations":[],"initialState":{"affineTransform":[1,0,0,1,0,0],"masksToBounds":false,"rotation":0,"scale":1,"position":{"pointX":295.5,"pointY":214.34745788574219},"width":401,"sublayerTransform":[1,0,0,0,0,1,0,0,0,0,1,0,0,0,0,1],"contentsRect":{"y":0,"x":0,"width":1,"height":1},"opacity":1,"edgeAntialiasingMask":251658240,"height":55,"hidden":false,"anchorPoint":{"pointX":0.5,"pointY":0.5}},"layers":[{"animations":[],"layers":[],"texturedRectangle":{"singleTextureOpacity":1,"textXHeight":0.51700000000000002,"textBaseline":0.7803152171048251,"isBackgroundTexture":true,"isVerticalText":false,"textColor":[0,0,0,1],"textureType":6},"initialState":{"affineTransform":[1,0,0,1,0,0],"masksToBounds":false,"rotation":0,"scale":1,"position":{"pointX":204.5,"pointY":42.652542114257812},"width":401,"sublayerTransform":[1,0,0,0,0,1,0,0,0,0,1,0,0,0,0,1],"contentsRect":{"y":0,"x":0,"width":1,"height":1},"opacity":1,"edgeAntialiasingMask":0,"height":55,"hidden":false,"anchorPoint":{"pointX":0.5,"pointY":0.5}},"texture":"467950B8C34586EDD279AE172F705699"}]}]},{"animations":[],"initialState":{"affineTransform":[1,0,0,1,0,0],"masksToBounds":false,"rotation":0,"scale":1,"position":{"pointX":960,"pointY":540},"width":1920,"sublayerTransform":[1,0,0,0,0,1,0,0,0,0,1,0,0,0,0,1],"contentsRect":{"y":0,"x":0,"width":1,"height":1},"opacity":1,"edgeAntialiasingMask":251658240,"height":1080,"hidden":false,"anchorPoint":{"pointX":0.5,"pointY":0.5}},"layers":[{"animations":[],"initialState":{"affineTransform":[1,0,0,1,0,0],"masksToBounds":false,"rotation":0,"scale":1,"position":{"pointX":961.4075927734375,"pointY":361.04428100585938},"width":600,"sublayerTransform":[1,0,0,0,0,1,0,0,0,0,1,0,0,0,0,1],"contentsRect":{"y":0,"x":0,"width":1,"height":1},"opacity":1,"edgeAntialiasingMask":251658240,"height":125,"hidden":false,"anchorPoint":{"pointX":0.5,"pointY":0.5}},"layers":[{"animations":[],"layers":[],"texturedRectangle":{"isBackgroundTexture":true,"singleTextureOpacity":1,"textureType":5,"textBaseline":0,"textXHeight":0,"isVerticalText":false},"initialState":{"affineTransform":[1,0,0,1,0,0],"masksToBounds":false,"rotation":0,"scale":1,"position":{"pointX":298.5924072265625,"pointY":60.955718994140625},"width":600,"sublayerTransform":[1,0,0,0,0,1,0,0,0,0,1,0,0,0,0,1],"contentsRect":{"y":0,"x":0,"width":1,"height":1},"opacity":1,"edgeAntialiasingMask":0,"height":125,"hidden":false,"anchorPoint":{"pointX":0.5,"pointY":0.5}},"texture":"1FF09739281378389A7864A2FABF1646"}]}]},{"animations":[],"initialState":{"affineTransform":[1,0,0,1,0,0],"masksToBounds":false,"rotation":0,"scale":1,"position":{"pointX":960,"pointY":540},"width":1920,"sublayerTransform":[1,0,0,0,0,1,0,0,0,0,1,0,0,0,0,1],"contentsRect":{"y":0,"x":0,"width":1,"height":1},"opacity":1,"edgeAntialiasingMask":251658240,"height":1080,"hidden":false,"anchorPoint":{"pointX":0.5,"pointY":0.5}},"layers":[{"animations":[],"initialState":{"affineTransform":[1,0,0,1,0,0],"masksToBounds":false,"rotation":0,"scale":1,"position":{"pointX":708.42601013183594,"pointY":556.29769897460938},"width":1119,"sublayerTransform":[1,0,0,0,0,1,0,0,0,0,1,0,0,0,0,1],"contentsRect":{"y":0,"x":0,"width":1,"height":1},"opacity":1,"edgeAntialiasingMask":251658240,"height":107,"hidden":false,"anchorPoint":{"pointX":0.5,"pointY":0.5}},"objectID":"08632DD1-A4B9-417E-9ACE-10EFF3882177","layers":[{"animations":[],"layers":[],"texturedRectangle":{"isBackgroundTexture":true,"singleTextureOpacity":1,"textureType":5,"textBaseline":0,"textXHeight":0,"isVerticalText":false},"initialState":{"affineTransform":[1,0,0,1,0,0],"masksToBounds":false,"rotation":0,"scale":1,"position":{"pointX":546.57398986816406,"pointY":40.702301025390625},"width":1119,"sublayerTransform":[1,0,0,0,0,1,0,0,0,0,1,0,0,0,0,1],"contentsRect":{"y":0,"x":0,"width":1,"height":1},"opacity":1,"edgeAntialiasingMask":0,"height":107,"hidden":true,"anchorPoint":{"pointX":0.5,"pointY":0.5}},"texture":"234DC0114C5052C599F20172FEC4564C"}]}]},{"animations":[],"initialState":{"affineTransform":[1,0,0,1,0,0],"masksToBounds":false,"rotation":0,"scale":1,"position":{"pointX":960,"pointY":540},"width":1920,"sublayerTransform":[1,0,0,0,0,1,0,0,0,0,1,0,0,0,0,1],"contentsRect":{"y":0,"x":0,"width":1,"height":1},"opacity":1,"edgeAntialiasingMask":251658240,"height":1080,"hidden":false,"anchorPoint":{"pointX":0.5,"pointY":0.5}},"layers":[{"animations":[],"initialState":{"affineTransform":[1,0,0,1,0,0],"masksToBounds":false,"rotation":0,"scale":1,"position":{"pointX":1535.6632080078125,"pointY":569.2515869140625},"width":609,"sublayerTransform":[1,0,0,0,0,1,0,0,0,0,1,0,0,0,0,1],"contentsRect":{"y":0,"x":0,"width":1,"height":1},"opacity":1,"edgeAntialiasingMask":251658240,"height":419,"hidden":false,"anchorPoint":{"pointX":0.5,"pointY":0.5}},"objectID":"D47F1AD5-8832-40FA-80BE-415E49EDE9AD","layers":[{"animations":[],"layers":[],"texturedRectangle":{"isBackgroundTexture":true,"singleTextureOpacity":1,"textureType":5,"textBaseline":0,"textXHeight":0,"isVerticalText":false},"initialState":{"affineTransform":[1,0,0,1,0,0],"masksToBounds":false,"rotation":0,"scale":1,"position":{"pointX":322.3367919921875,"pointY":207.7484130859375},"width":609,"sublayerTransform":[1,0,0,0,0,1,0,0,0,0,1,0,0,0,0,1],"contentsRect":{"y":0,"x":0,"width":1,"height":1},"opacity":1,"edgeAntialiasingMask":0,"height":419,"hidden":true,"anchorPoint":{"pointX":0.5,"pointY":0.5}},"texture":"12B92BA02378E659CCFC9EBD056CFFC8"}]}]},{"animations":[],"initialState":{"affineTransform":[1,0,0,1,0,0],"masksToBounds":false,"rotation":0,"scale":1,"position":{"pointX":960,"pointY":540},"width":1920,"sublayerTransform":[1,0,0,0,0,1,0,0,0,0,1,0,0,0,0,1],"contentsRect":{"y":0,"x":0,"width":1,"height":1},"opacity":1,"edgeAntialiasingMask":251658240,"height":1080,"hidden":false,"anchorPoint":{"pointX":0.5,"pointY":0.5}},"layers":[{"animations":[],"initialState":{"affineTransform":[1,0,0,1,0,0],"masksToBounds":false,"rotation":0,"scale":1,"position":{"pointX":1019.4260101318359,"pointY":996.5687255859375},"width":1739,"sublayerTransform":[1,0,0,0,0,1,0,0,0,0,1,0,0,0,0,1],"contentsRect":{"y":0,"x":0,"width":1,"height":1},"opacity":1,"edgeAntialiasingMask":251658240,"height":247,"hidden":false,"anchorPoint":{"pointX":0.5,"pointY":0.5}},"objectID":"48DFFD9D-57DB-48F9-AE6E-7021ED0DEAA4","layers":[{"animations":[],"layers":[],"texturedRectangle":{"isBackgroundTexture":true,"singleTextureOpacity":1,"textureType":5,"textBaseline":0,"textXHeight":0,"isVerticalText":false},"initialState":{"affineTransform":[1,0,0,1,0,0],"masksToBounds":false,"rotation":0,"scale":1,"position":{"pointX":855.57398986816406,"pointY":55.4312744140625},"width":1739,"sublayerTransform":[1,0,0,0,0,1,0,0,0,0,1,0,0,0,0,1],"contentsRect":{"y":0,"x":0,"width":1,"height":1},"opacity":1,"edgeAntialiasingMask":0,"height":247,"hidden":true,"anchorPoint":{"pointX":0.5,"pointY":0.5}},"texture":"88DA894CD5271F0FBBEEE8AF7E1ED0DA"}]}]}]}},{"effects":[{"beginTime":0,"baseLayer":{"animations":[],"initialState":{"affineTransform":[1,0,0,1,0,0],"masksToBounds":false,"rotation":0,"scale":1,"position":{"pointX":1535.6632080078125,"pointY":569.2515869140625},"width":609,"sublayerTransform":[1,0,0,0,0,1,0,0,0,0,1,0,0,0,0,1],"contentsRect":{"y":0,"x":0,"width":1,"height":1},"opacity":1,"edgeAntialiasingMask":251658240,"height":419,"hidden":false,"anchorPoint":{"pointX":0.5,"pointY":0.5}},"objectID":"D47F1AD5-8832-40FA-80BE-415E49EDE9AD","layers":[{"animations":[],"initialState":{"affineTransform":[1,0,0,1,0,0],"masksToBounds":false,"rotation":0,"scale":1,"position":{"pointX":-271.1632080078125,"pointY":180.2484130859375},"width":609,"sublayerTransform":[1,0,0,0,0,1,0,0,0,0,1,-0.00035007912466775983,0,0,0,1],"contentsRect":{"y":0,"x":0,"width":1,"height":1},"opacity":1,"edgeAntialiasingMask":251658240,"height":419,"hidden":false,"anchorPoint":{"pointX":-0.44525978326405996,"pointY":0.43018714340319214}},"layers":[{"animations":[{"additive":false,"timeOffset":0,"beginTime":1e-100,"repeatCount":0,"fillMode":"both","duration":0.01,"autoreverses":false,"animations":[{"additive":false,"timeOffset":0,"beginTime":0,"from":{"scalar":true},"repeatCount":0,"fillMode":"both","duration":0.0001,"autoreverses":false,"property":"hidden","to":{"scalar":false},"removedOnCompletion":true},{"additive":false,"timeOffset":0,"beginTime":0.0001,"from":{"scalar":false},"repeatCount":0,"fillMode":"forwards","duration":0.0099000000000000008,"autoreverses":false,"property":"hidden","to":{"scalar":false},"removedOnCompletion":true}],"removedOnCompletion":false}],"layers":[],"texturedRectangle":{"isBackgroundTexture":true,"singleTextureOpacity":1,"textureType":5,"textBaseline":0,"textXHeight":0,"isVerticalText":false},"initialState":{"affineTransform":[1,0,0,1,0,0],"masksToBounds":false,"rotation":0,"scale":1,"position":{"pointX":322.3367919921875,"pointY":207.7484130859375},"width":609,"sublayerTransform":[1,0,0,0,0,1,0,0,0,0,1,0,0,0,0,1],"contentsRect":{"y":0,"x":0,"width":1,"height":1},"opacity":1,"edgeAntialiasingMask":0,"height":419,"hidden":true,"anchorPoint":{"pointX":0.5,"pointY":0.5}},"texture":"12B92BA02378E659CCFC9EBD056CFFC8"}]}]},"effects":[],"duration":0.01,"type":"buildIn","attributes":{"direction":0},"name":"apple:appear","objectID":"D47F1AD5-8832-40FA-80BE-415E49EDE9AD"}],"automaticPlay":false,"hyperlinks":[],"accessibility":[{"text":"Computing P(x)","targetRectangle":{"y":190.44745779037476,"x":98.599999904632568,"width":403.2600000000001,"height":66.404617309570312}},{"text":"pasted-image.pdf","targetRectangle":{"y":359.92463073134422,"x":1372.4314422607422,"width":484.055419921875,"height":415.23040771484375}},{"text":"The direct way:","targetRectangle":{"y":506.79770004749298,"x":152.92601013183594,"width":399.29999999999995,"height":66.404617309570312}},{"text":"output","targetRectangle":{"y":953.3394775390625,"x":1241.7630462646484,"width":113.45100000000002,"height":44.908004760742301}},{"text":"pasted-image.pdf","targetRectangle":{"y":298.54428100585938,"x":661.4075927734375,"width":597.18487548828125,"height":122.41463470458984}},{"text":"Model-based Information Estimate","targetRectangle":{"y":89,"x":99,"width":1352.0950012159346,"height":100.53440856933594}},{"text":"output","targetRectangle":{"y":685.27264404296864,"x":1261.1632080078125,"width":113.45100000000002,"height":44.908004760742301}},{"text":"pasted-image.pdf","targetRectangle":{"y":521.5151424407959,"x":661.40751647949219,"width":592.26043701171875,"height":73.604621887207031}},{"text":"inputs","targetRectangle":{"y":819.30609512329102,"x":1241.7630462646484,"width":106.9380000000001,"height":44.908004760742301}},{"text":"inputs","targetRectangle":{"y":456.60183306884767,"x":1319.3929481506348,"width":44.908004760742188,"height":106.93799999999999}},{"text":"￼","targetRectangle":{"y":1033.9999701976776,"x":949.49999516521348,"width":20.015999999999963,"height":21.496002197265625}},{"text":"Sampling segment by segment:","targetRectangle":{"y":877.06872665882111,"x":152.92601013183594,"width":826.86999999999989,"height":66.404617309570312}},{"text":"pasted-image.pdf","targetRectangle":{"y":806.94476318359375,"x":1373.2510833740234,"width":500.37890625,"height":243.20823669433594}}],"baseLayer":{"animations":[],"initialState":{"affineTransform":[1,0,0,1,0,0],"masksToBounds":false,"rotation":0,"scale":1,"position":{"pointX":960,"pointY":540},"width":1920,"sublayerTransform":[1,0,0,0,0,1,0,0,0,0,1,0,0,0,0,1],"contentsRect":{"y":0,"x":0,"width":1,"height":1},"opacity":1,"edgeAntialiasingMask":251658240,"height":1080,"hidden":false,"anchorPoint":{"pointX":0.5,"pointY":0.5}},"layers":[{"animations":[],"initialState":{"affineTransform":[1,0,0,1,0,0],"masksToBounds":false,"rotation":0,"scale":1,"position":{"pointX":960,"pointY":540},"width":1920,"sublayerTransform":[1,0,0,0,0,1,0,0,0,0,1,0,0,0,0,1],"contentsRect":{"y":0,"x":0,"width":1,"height":1},"opacity":1,"edgeAntialiasingMask":251658240,"height":1080,"hidden":false,"anchorPoint":{"pointX":0.5,"pointY":0.5}},"layers":[{"animations":[],"initialState":{"affineTransform":[1,0,0,1,0,0],"masksToBounds":false,"rotation":0,"scale":1,"position":{"pointX":960,"pointY":540},"width":1920,"sublayerTransform":[1,0,0,0,0,1,0,0,0,0,1,0,0,0,0,1],"contentsRect":{"y":0,"x":0,"width":1,"height":1},"opacity":1,"edgeAntialiasingMask":251658240,"height":1080,"hidden":false,"anchorPoint":{"pointX":0.5,"pointY":0.5}},"layers":[{"animations":[],"layers":[],"texturedRectangle":{"isBackgroundTexture":true,"singleTextureOpacity":1,"textureType":1,"textBaseline":0,"textXHeight":0,"isVerticalText":false},"initialState":{"affineTransform":[1,0,0,1,0,0],"masksToBounds":false,"rotation":0,"scale":1,"position":{"pointX":960,"pointY":540},"width":1920,"sublayerTransform":[1,0,0,0,0,1,0,0,0,0,1,0,0,0,0,1],"contentsRect":{"y":0,"x":0,"width":1,"height":1},"opacity":1,"edgeAntialiasingMask":0,"height":1080,"hidden":false,"anchorPoint":{"pointX":0.5,"pointY":0.5}},"texture":"C25C25FF361FB24FC35F6B120D2F252D"}]}]},{"animations":[],"initialState":{"affineTransform":[1,0,0,1,0,0],"masksToBounds":false,"rotation":0,"scale":1,"position":{"pointX":960,"pointY":540},"width":1920,"sublayerTransform":[1,0,0,0,0,1,0,0,0,0,1,0,0,0,0,1],"contentsRect":{"y":0,"x":0,"width":1,"height":1},"opacity":1,"edgeAntialiasingMask":251658240,"height":1080,"hidden":false,"anchorPoint":{"pointX":0.5,"pointY":0.5}},"layers":[{"animations":[],"initialState":{"affineTransform":[1,0,0,1,0,0],"masksToBounds":false,"rotation":0,"scale":1,"position":{"pointX":769.5,"pointY":117.49999999999997},"width":1349,"sublayerTransform":[1,0,0,0,0,1,0,0,0,0,1,0,0,0,0,1],"contentsRect":{"y":0,"x":0,"width":1,"height":1},"opacity":1,"edgeAntialiasingMask":251658240,"height":65,"hidden":false,"anchorPoint":{"pointX":0.5,"pointY":0.5}},"layers":[{"animations":[],"layers":[],"texturedRectangle":{"singleTextureOpacity":1,"textXHeight":0.67607692307692313,"textBaseline":0.9552278958834135,"isBackgroundTexture":true,"isVerticalText":false,"textColor":[0,0,0,1],"textureType":6},"initialState":{"affineTransform":[1,0,0,1,0,0],"masksToBounds":false,"rotation":0,"scale":1,"position":{"pointX":682.5,"pointY":56.500000000000028},"width":1349,"sublayerTransform":[1,0,0,0,0,1,0,0,0,0,1,0,0,0,0,1],"contentsRect":{"y":0,"x":0,"width":1,"height":1},"opacity":1,"edgeAntialiasingMask":0,"height":65,"hidden":false,"anchorPoint":{"pointX":0.5,"pointY":0.5}},"texture":"F1606019E2FC33A158CFAB6CB02DEEE4"}]}]},{"animations":[],"initialState":{"affineTransform":[1,0,0,1,0,0],"masksToBounds":false,"rotation":0,"scale":1,"position":{"pointX":960,"pointY":540},"width":1920,"sublayerTransform":[1,0,0,0,0,1,0,0,0,0,1,0,0,0,0,1],"contentsRect":{"y":0,"x":0,"width":1,"height":1},"opacity":1,"edgeAntialiasingMask":251658240,"height":1080,"hidden":false,"anchorPoint":{"pointX":0.5,"pointY":0.5}},"layers":[{"animations":[],"initialState":{"affineTransform":[1,0,0,1,0,0],"masksToBounds":false,"rotation":0,"scale":1,"position":{"pointX":956.49999516521348,"pointY":1038.4999701976776},"width":23,"sublayerTransform":[1,0,0,0,0,1,0,0,0,0,1,0,0,0,0,1],"contentsRect":{"y":0,"x":0,"width":1,"height":1},"opacity":1,"edgeAntialiasingMask":251658240,"height":17,"hidden":false,"anchorPoint":{"pointX":0.5,"pointY":0.5}},"layers":[{"animations":[],"layers":[],"texturedRectangle":{"singleTextureOpacity":1,"textXHeight":0.54741176470588226,"textBaseline":0.92129520808949195,"isBackgroundTexture":true,"isVerticalText":false,"textColor":[0,0,0,1],"textureType":6},"initialState":{"affineTransform":[1,0,0,1,0,0],"masksToBounds":false,"rotation":0,"scale":1,"position":{"pointX":13.500004834786523,"pointY":14.500029802322388},"width":23,"sublayerTransform":[1,0,0,0,0,1,0,0,0,0,1,0,0,0,0,1],"contentsRect":{"y":0,"x":0,"width":1,"height":1},"opacity":1,"edgeAntialiasingMask":0,"height":17,"hidden":false,"anchorPoint":{"pointX":0.5,"pointY":0.5}},"texture":"C398C6CBE44576E26EDBCA30676F307F"}]}]},{"animations":[],"initialState":{"affineTransform":[1,0,0,1,0,0],"masksToBounds":false,"rotation":0,"scale":1,"position":{"pointX":960,"pointY":540},"width":1920,"sublayerTransform":[1,0,0,0,0,1,0,0,0,0,1,0,0,0,0,1],"contentsRect":{"y":0,"x":0,"width":1,"height":1},"opacity":1,"edgeAntialiasingMask":251658240,"height":1080,"hidden":false,"anchorPoint":{"pointX":0.5,"pointY":0.5}},"layers":[{"animations":[],"initialState":{"affineTransform":[1,0,0,1,0,0],"masksToBounds":false,"rotation":0,"scale":1,"position":{"pointX":295.5,"pointY":214.34745788574219},"width":401,"sublayerTransform":[1,0,0,0,0,1,0,0,0,0,1,0,0,0,0,1],"contentsRect":{"y":0,"x":0,"width":1,"height":1},"opacity":1,"edgeAntialiasingMask":251658240,"height":55,"hidden":false,"anchorPoint":{"pointX":0.5,"pointY":0.5}},"layers":[{"animations":[],"layers":[],"texturedRectangle":{"singleTextureOpacity":1,"textXHeight":0.51700000000000002,"textBaseline":0.7803152171048251,"isBackgroundTexture":true,"isVerticalText":false,"textColor":[0,0,0,1],"textureType":6},"initialState":{"affineTransform":[1,0,0,1,0,0],"masksToBounds":false,"rotation":0,"scale":1,"position":{"pointX":204.5,"pointY":42.652542114257812},"width":401,"sublayerTransform":[1,0,0,0,0,1,0,0,0,0,1,0,0,0,0,1],"contentsRect":{"y":0,"x":0,"width":1,"height":1},"opacity":1,"edgeAntialiasingMask":0,"height":55,"hidden":false,"anchorPoint":{"pointX":0.5,"pointY":0.5}},"texture":"467950B8C34586EDD279AE172F705699"}]}]},{"animations":[],"initialState":{"affineTransform":[1,0,0,1,0,0],"masksToBounds":false,"rotation":0,"scale":1,"position":{"pointX":960,"pointY":540},"width":1920,"sublayerTransform":[1,0,0,0,0,1,0,0,0,0,1,0,0,0,0,1],"contentsRect":{"y":0,"x":0,"width":1,"height":1},"opacity":1,"edgeAntialiasingMask":251658240,"height":1080,"hidden":false,"anchorPoint":{"pointX":0.5,"pointY":0.5}},"layers":[{"animations":[],"initialState":{"affineTransform":[1,0,0,1,0,0],"masksToBounds":false,"rotation":0,"scale":1,"position":{"pointX":961.4075927734375,"pointY":361.04428100585938},"width":600,"sublayerTransform":[1,0,0,0,0,1,0,0,0,0,1,0,0,0,0,1],"contentsRect":{"y":0,"x":0,"width":1,"height":1},"opacity":1,"edgeAntialiasingMask":251658240,"height":125,"hidden":false,"anchorPoint":{"pointX":0.5,"pointY":0.5}},"layers":[{"animations":[],"layers":[],"texturedRectangle":{"isBackgroundTexture":true,"singleTextureOpacity":1,"textureType":5,"textBaseline":0,"textXHeight":0,"isVerticalText":false},"initialState":{"affineTransform":[1,0,0,1,0,0],"masksToBounds":false,"rotation":0,"scale":1,"position":{"pointX":298.5924072265625,"pointY":60.955718994140625},"width":600,"sublayerTransform":[1,0,0,0,0,1,0,0,0,0,1,0,0,0,0,1],"contentsRect":{"y":0,"x":0,"width":1,"height":1},"opacity":1,"edgeAntialiasingMask":0,"height":125,"hidden":false,"anchorPoint":{"pointX":0.5,"pointY":0.5}},"texture":"1FF09739281378389A7864A2FABF1646"}]}]},{"animations":[],"initialState":{"affineTransform":[1,0,0,1,0,0],"masksToBounds":false,"rotation":0,"scale":1,"position":{"pointX":960,"pointY":540},"width":1920,"sublayerTransform":[1,0,0,0,0,1,0,0,0,0,1,0,0,0,0,1],"contentsRect":{"y":0,"x":0,"width":1,"height":1},"opacity":1,"edgeAntialiasingMask":251658240,"height":1080,"hidden":false,"anchorPoint":{"pointX":0.5,"pointY":0.5}},"layers":[{"animations":[],"initialState":{"affineTransform":[1,0,0,1,0,0],"masksToBounds":false,"rotation":0,"scale":1,"position":{"pointX":708.42601013183594,"pointY":556.29769897460938},"width":1119,"sublayerTransform":[1,0,0,0,0,1,0,0,0,0,1,0,0,0,0,1],"contentsRect":{"y":0,"x":0,"width":1,"height":1},"opacity":1,"edgeAntialiasingMask":251658240,"height":107,"hidden":false,"anchorPoint":{"pointX":0.5,"pointY":0.5}},"objectID":"08632DD1-A4B9-417E-9ACE-10EFF3882177","layers":[{"animations":[],"layers":[],"texturedRectangle":{"isBackgroundTexture":true,"singleTextureOpacity":1,"textureType":5,"textBaseline":0,"textXHeight":0,"isVerticalText":false},"initialState":{"affineTransform":[1,0,0,1,0,0],"masksToBounds":false,"rotation":0,"scale":1,"position":{"pointX":546.57398986816406,"pointY":40.702301025390625},"width":1119,"sublayerTransform":[1,0,0,0,0,1,0,0,0,0,1,0,0,0,0,1],"contentsRect":{"y":0,"x":0,"width":1,"height":1},"opacity":1,"edgeAntialiasingMask":0,"height":107,"hidden":false,"anchorPoint":{"pointX":0.5,"pointY":0.5}},"texture":"234DC0114C5052C599F20172FEC4564C"}]}]},{"animations":[],"initialState":{"affineTransform":[1,0,0,1,0,0],"masksToBounds":false,"rotation":0,"scale":1,"position":{"pointX":960,"pointY":540},"width":1920,"sublayerTransform":[1,0,0,0,0,1,0,0,0,0,1,0,0,0,0,1],"contentsRect":{"y":0,"x":0,"width":1,"height":1},"opacity":1,"edgeAntialiasingMask":251658240,"height":1080,"hidden":false,"anchorPoint":{"pointX":0.5,"pointY":0.5}},"layers":[{"animations":[],"initialState":{"affineTransform":[1,0,0,1,0,0],"masksToBounds":false,"rotation":0,"scale":1,"position":{"pointX":1535.6632080078125,"pointY":569.2515869140625},"width":609,"sublayerTransform":[1,0,0,0,0,1,0,0,0,0,1,0,0,0,0,1],"contentsRect":{"y":0,"x":0,"width":1,"height":1},"opacity":1,"edgeAntialiasingMask":251658240,"height":419,"hidden":false,"anchorPoint":{"pointX":0.5,"pointY":0.5}},"objectID":"D47F1AD5-8832-40FA-80BE-415E49EDE9AD","layers":[{"animations":[],"layers":[],"texturedRectangle":{"isBackgroundTexture":true,"singleTextureOpacity":1,"textureType":5,"textBaseline":0,"textXHeight":0,"isVerticalText":false},"initialState":{"affineTransform":[1,0,0,1,0,0],"masksToBounds":false,"rotation":0,"scale":1,"position":{"pointX":322.3367919921875,"pointY":207.7484130859375},"width":609,"sublayerTransform":[1,0,0,0,0,1,0,0,0,0,1,0,0,0,0,1],"contentsRect":{"y":0,"x":0,"width":1,"height":1},"opacity":1,"edgeAntialiasingMask":0,"height":419,"hidden":true,"anchorPoint":{"pointX":0.5,"pointY":0.5}},"texture":"12B92BA02378E659CCFC9EBD056CFFC8"}]}]},{"animations":[],"initialState":{"affineTransform":[1,0,0,1,0,0],"masksToBounds":false,"rotation":0,"scale":1,"position":{"pointX":960,"pointY":540},"width":1920,"sublayerTransform":[1,0,0,0,0,1,0,0,0,0,1,0,0,0,0,1],"contentsRect":{"y":0,"x":0,"width":1,"height":1},"opacity":1,"edgeAntialiasingMask":251658240,"height":1080,"hidden":false,"anchorPoint":{"pointX":0.5,"pointY":0.5}},"layers":[{"animations":[],"initialState":{"affineTransform":[1,0,0,1,0,0],"masksToBounds":false,"rotation":0,"scale":1,"position":{"pointX":1019.4260101318359,"pointY":996.5687255859375},"width":1739,"sublayerTransform":[1,0,0,0,0,1,0,0,0,0,1,0,0,0,0,1],"contentsRect":{"y":0,"x":0,"width":1,"height":1},"opacity":1,"edgeAntialiasingMask":251658240,"height":247,"hidden":false,"anchorPoint":{"pointX":0.5,"pointY":0.5}},"objectID":"48DFFD9D-57DB-48F9-AE6E-7021ED0DEAA4","layers":[{"animations":[],"layers":[],"texturedRectangle":{"isBackgroundTexture":true,"singleTextureOpacity":1,"textureType":5,"textBaseline":0,"textXHeight":0,"isVerticalText":false},"initialState":{"affineTransform":[1,0,0,1,0,0],"masksToBounds":false,"rotation":0,"scale":1,"position":{"pointX":855.57398986816406,"pointY":55.4312744140625},"width":1739,"sublayerTransform":[1,0,0,0,0,1,0,0,0,0,1,0,0,0,0,1],"contentsRect":{"y":0,"x":0,"width":1,"height":1},"opacity":1,"edgeAntialiasingMask":0,"height":247,"hidden":true,"anchorPoint":{"pointX":0.5,"pointY":0.5}},"texture":"88DA894CD5271F0FBBEEE8AF7E1ED0DA"}]}]}]}},{"effects":[{"beginTime":0,"baseLayer":{"animations":[],"initialState":{"affineTransform":[1,0,0,1,0,0],"masksToBounds":false,"rotation":0,"scale":1,"position":{"pointX":1019.4260101318359,"pointY":996.5687255859375},"width":1739,"sublayerTransform":[1,0,0,0,0,1,0,0,0,0,1,0,0,0,0,1],"contentsRect":{"y":0,"x":0,"width":1,"height":1},"opacity":1,"edgeAntialiasingMask":251658240,"height":247,"hidden":false,"anchorPoint":{"pointX":0.5,"pointY":0.5}},"objectID":"48DFFD9D-57DB-48F9-AE6E-7021ED0DEAA4","layers":[{"animations":[],"initialState":{"affineTransform":[1,0,0,1,0,0],"masksToBounds":false,"rotation":0,"scale":1,"position":{"pointX":810.07398986816406,"pointY":-333.0687255859375},"width":1739,"sublayerTransform":[1,0,0,0,0,1,0,0,0,0,1,-0.00035007912466775983,0,0,0,1],"contentsRect":{"y":0,"x":0,"width":1,"height":1},"opacity":1,"edgeAntialiasingMask":251658240,"height":247,"hidden":false,"anchorPoint":{"pointX":0.465827481235287,"pointY":-1.3484563788904351}},"layers":[{"animations":[{"additive":false,"timeOffset":0,"beginTime":1e-100,"repeatCount":0,"fillMode":"both","duration":0.01,"autoreverses":false,"animations":[{"additive":false,"timeOffset":0,"beginTime":0,"from":{"scalar":true},"repeatCount":0,"fillMode":"both","duration":0.0001,"autoreverses":false,"property":"hidden","to":{"scalar":false},"removedOnCompletion":true},{"additive":false,"timeOffset":0,"beginTime":0.0001,"from":{"scalar":false},"repeatCount":0,"fillMode":"forwards","duration":0.0099000000000000008,"autoreverses":false,"property":"hidden","to":{"scalar":false},"removedOnCompletion":true}],"removedOnCompletion":false}],"layers":[],"texturedRectangle":{"isBackgroundTexture":true,"singleTextureOpacity":1,"textureType":5,"textBaseline":0,"textXHeight":0,"isVerticalText":false},"initialState":{"affineTransform":[1,0,0,1,0,0],"masksToBounds":false,"rotation":0,"scale":1,"position":{"pointX":855.57398986816406,"pointY":55.4312744140625},"width":1739,"sublayerTransform":[1,0,0,0,0,1,0,0,0,0,1,0,0,0,0,1],"contentsRect":{"y":0,"x":0,"width":1,"height":1},"opacity":1,"edgeAntialiasingMask":0,"height":247,"hidden":true,"anchorPoint":{"pointX":0.5,"pointY":0.5}},"texture":"88DA894CD5271F0FBBEEE8AF7E1ED0DA"}]}]},"effects":[],"duration":0.01,"type":"buildIn","attributes":{"direction":0},"name":"apple:appear","objectID":"48DFFD9D-57DB-48F9-AE6E-7021ED0DEAA4"}],"automaticPlay":false,"hyperlinks":[],"accessibility":[{"text":"Computing P(x)","targetRectangle":{"y":190.44745779037476,"x":98.599999904632568,"width":403.2600000000001,"height":66.404617309570312}},{"text":"pasted-image.pdf","targetRectangle":{"y":359.92463073134422,"x":1372.4314422607422,"width":484.055419921875,"height":415.23040771484375}},{"text":"The direct way:","targetRectangle":{"y":506.79770004749298,"x":152.92601013183594,"width":399.29999999999995,"height":66.404617309570312}},{"text":"output","targetRectangle":{"y":953.3394775390625,"x":1241.7630462646484,"width":113.45100000000002,"height":44.908004760742301}},{"text":"pasted-image.pdf","targetRectangle":{"y":298.54428100585938,"x":661.4075927734375,"width":597.18487548828125,"height":122.41463470458984}},{"text":"Model-based Information Estimate","targetRectangle":{"y":89,"x":99,"width":1352.0950012159346,"height":100.53440856933594}},{"text":"output","targetRectangle":{"y":685.27264404296864,"x":1261.1632080078125,"width":113.45100000000002,"height":44.908004760742301}},{"text":"pasted-image.pdf","targetRectangle":{"y":521.5151424407959,"x":661.40751647949219,"width":592.26043701171875,"height":73.604621887207031}},{"text":"inputs","targetRectangle":{"y":819.30609512329102,"x":1241.7630462646484,"width":106.9380000000001,"height":44.908004760742301}},{"text":"inputs","targetRectangle":{"y":456.60183306884767,"x":1319.3929481506348,"width":44.908004760742188,"height":106.93799999999999}},{"text":"￼","targetRectangle":{"y":1033.9999701976776,"x":949.49999516521348,"width":20.015999999999963,"height":21.496002197265625}},{"text":"Sampling segment by segment:","targetRectangle":{"y":877.06872665882111,"x":152.92601013183594,"width":826.86999999999989,"height":66.404617309570312}},{"text":"pasted-image.pdf","targetRectangle":{"y":806.94476318359375,"x":1373.2510833740234,"width":500.37890625,"height":243.20823669433594}}],"baseLayer":{"animations":[],"initialState":{"affineTransform":[1,0,0,1,0,0],"masksToBounds":false,"rotation":0,"scale":1,"position":{"pointX":960,"pointY":540},"width":1920,"sublayerTransform":[1,0,0,0,0,1,0,0,0,0,1,0,0,0,0,1],"contentsRect":{"y":0,"x":0,"width":1,"height":1},"opacity":1,"edgeAntialiasingMask":251658240,"height":1080,"hidden":false,"anchorPoint":{"pointX":0.5,"pointY":0.5}},"layers":[{"animations":[],"initialState":{"affineTransform":[1,0,0,1,0,0],"masksToBounds":false,"rotation":0,"scale":1,"position":{"pointX":960,"pointY":540},"width":1920,"sublayerTransform":[1,0,0,0,0,1,0,0,0,0,1,0,0,0,0,1],"contentsRect":{"y":0,"x":0,"width":1,"height":1},"opacity":1,"edgeAntialiasingMask":251658240,"height":1080,"hidden":false,"anchorPoint":{"pointX":0.5,"pointY":0.5}},"layers":[{"animations":[],"initialState":{"affineTransform":[1,0,0,1,0,0],"masksToBounds":false,"rotation":0,"scale":1,"position":{"pointX":960,"pointY":540},"width":1920,"sublayerTransform":[1,0,0,0,0,1,0,0,0,0,1,0,0,0,0,1],"contentsRect":{"y":0,"x":0,"width":1,"height":1},"opacity":1,"edgeAntialiasingMask":251658240,"height":1080,"hidden":false,"anchorPoint":{"pointX":0.5,"pointY":0.5}},"layers":[{"animations":[],"layers":[],"texturedRectangle":{"isBackgroundTexture":true,"singleTextureOpacity":1,"textureType":1,"textBaseline":0,"textXHeight":0,"isVerticalText":false},"initialState":{"affineTransform":[1,0,0,1,0,0],"masksToBounds":false,"rotation":0,"scale":1,"position":{"pointX":960,"pointY":540},"width":1920,"sublayerTransform":[1,0,0,0,0,1,0,0,0,0,1,0,0,0,0,1],"contentsRect":{"y":0,"x":0,"width":1,"height":1},"opacity":1,"edgeAntialiasingMask":0,"height":1080,"hidden":false,"anchorPoint":{"pointX":0.5,"pointY":0.5}},"texture":"C25C25FF361FB24FC35F6B120D2F252D"}]}]},{"animations":[],"initialState":{"affineTransform":[1,0,0,1,0,0],"masksToBounds":false,"rotation":0,"scale":1,"position":{"pointX":960,"pointY":540},"width":1920,"sublayerTransform":[1,0,0,0,0,1,0,0,0,0,1,0,0,0,0,1],"contentsRect":{"y":0,"x":0,"width":1,"height":1},"opacity":1,"edgeAntialiasingMask":251658240,"height":1080,"hidden":false,"anchorPoint":{"pointX":0.5,"pointY":0.5}},"layers":[{"animations":[],"initialState":{"affineTransform":[1,0,0,1,0,0],"masksToBounds":false,"rotation":0,"scale":1,"position":{"pointX":769.5,"pointY":117.49999999999997},"width":1349,"sublayerTransform":[1,0,0,0,0,1,0,0,0,0,1,0,0,0,0,1],"contentsRect":{"y":0,"x":0,"width":1,"height":1},"opacity":1,"edgeAntialiasingMask":251658240,"height":65,"hidden":false,"anchorPoint":{"pointX":0.5,"pointY":0.5}},"layers":[{"animations":[],"layers":[],"texturedRectangle":{"singleTextureOpacity":1,"textXHeight":0.67607692307692313,"textBaseline":0.9552278958834135,"isBackgroundTexture":true,"isVerticalText":false,"textColor":[0,0,0,1],"textureType":6},"initialState":{"affineTransform":[1,0,0,1,0,0],"masksToBounds":false,"rotation":0,"scale":1,"position":{"pointX":682.5,"pointY":56.500000000000028},"width":1349,"sublayerTransform":[1,0,0,0,0,1,0,0,0,0,1,0,0,0,0,1],"contentsRect":{"y":0,"x":0,"width":1,"height":1},"opacity":1,"edgeAntialiasingMask":0,"height":65,"hidden":false,"anchorPoint":{"pointX":0.5,"pointY":0.5}},"texture":"F1606019E2FC33A158CFAB6CB02DEEE4"}]}]},{"animations":[],"initialState":{"affineTransform":[1,0,0,1,0,0],"masksToBounds":false,"rotation":0,"scale":1,"position":{"pointX":960,"pointY":540},"width":1920,"sublayerTransform":[1,0,0,0,0,1,0,0,0,0,1,0,0,0,0,1],"contentsRect":{"y":0,"x":0,"width":1,"height":1},"opacity":1,"edgeAntialiasingMask":251658240,"height":1080,"hidden":false,"anchorPoint":{"pointX":0.5,"pointY":0.5}},"layers":[{"animations":[],"initialState":{"affineTransform":[1,0,0,1,0,0],"masksToBounds":false,"rotation":0,"scale":1,"position":{"pointX":956.49999516521348,"pointY":1038.4999701976776},"width":23,"sublayerTransform":[1,0,0,0,0,1,0,0,0,0,1,0,0,0,0,1],"contentsRect":{"y":0,"x":0,"width":1,"height":1},"opacity":1,"edgeAntialiasingMask":251658240,"height":17,"hidden":false,"anchorPoint":{"pointX":0.5,"pointY":0.5}},"layers":[{"animations":[],"layers":[],"texturedRectangle":{"singleTextureOpacity":1,"textXHeight":0.54741176470588226,"textBaseline":0.92129520808949195,"isBackgroundTexture":true,"isVerticalText":false,"textColor":[0,0,0,1],"textureType":6},"initialState":{"affineTransform":[1,0,0,1,0,0],"masksToBounds":false,"rotation":0,"scale":1,"position":{"pointX":13.500004834786523,"pointY":14.500029802322388},"width":23,"sublayerTransform":[1,0,0,0,0,1,0,0,0,0,1,0,0,0,0,1],"contentsRect":{"y":0,"x":0,"width":1,"height":1},"opacity":1,"edgeAntialiasingMask":0,"height":17,"hidden":false,"anchorPoint":{"pointX":0.5,"pointY":0.5}},"texture":"C398C6CBE44576E26EDBCA30676F307F"}]}]},{"animations":[],"initialState":{"affineTransform":[1,0,0,1,0,0],"masksToBounds":false,"rotation":0,"scale":1,"position":{"pointX":960,"pointY":540},"width":1920,"sublayerTransform":[1,0,0,0,0,1,0,0,0,0,1,0,0,0,0,1],"contentsRect":{"y":0,"x":0,"width":1,"height":1},"opacity":1,"edgeAntialiasingMask":251658240,"height":1080,"hidden":false,"anchorPoint":{"pointX":0.5,"pointY":0.5}},"layers":[{"animations":[],"initialState":{"affineTransform":[1,0,0,1,0,0],"masksToBounds":false,"rotation":0,"scale":1,"position":{"pointX":295.5,"pointY":214.34745788574219},"width":401,"sublayerTransform":[1,0,0,0,0,1,0,0,0,0,1,0,0,0,0,1],"contentsRect":{"y":0,"x":0,"width":1,"height":1},"opacity":1,"edgeAntialiasingMask":251658240,"height":55,"hidden":false,"anchorPoint":{"pointX":0.5,"pointY":0.5}},"layers":[{"animations":[],"layers":[],"texturedRectangle":{"singleTextureOpacity":1,"textXHeight":0.51700000000000002,"textBaseline":0.7803152171048251,"isBackgroundTexture":true,"isVerticalText":false,"textColor":[0,0,0,1],"textureType":6},"initialState":{"affineTransform":[1,0,0,1,0,0],"masksToBounds":false,"rotation":0,"scale":1,"position":{"pointX":204.5,"pointY":42.652542114257812},"width":401,"sublayerTransform":[1,0,0,0,0,1,0,0,0,0,1,0,0,0,0,1],"contentsRect":{"y":0,"x":0,"width":1,"height":1},"opacity":1,"edgeAntialiasingMask":0,"height":55,"hidden":false,"anchorPoint":{"pointX":0.5,"pointY":0.5}},"texture":"467950B8C34586EDD279AE172F705699"}]}]},{"animations":[],"initialState":{"affineTransform":[1,0,0,1,0,0],"masksToBounds":false,"rotation":0,"scale":1,"position":{"pointX":960,"pointY":540},"width":1920,"sublayerTransform":[1,0,0,0,0,1,0,0,0,0,1,0,0,0,0,1],"contentsRect":{"y":0,"x":0,"width":1,"height":1},"opacity":1,"edgeAntialiasingMask":251658240,"height":1080,"hidden":false,"anchorPoint":{"pointX":0.5,"pointY":0.5}},"layers":[{"animations":[],"initialState":{"affineTransform":[1,0,0,1,0,0],"masksToBounds":false,"rotation":0,"scale":1,"position":{"pointX":961.4075927734375,"pointY":361.04428100585938},"width":600,"sublayerTransform":[1,0,0,0,0,1,0,0,0,0,1,0,0,0,0,1],"contentsRect":{"y":0,"x":0,"width":1,"height":1},"opacity":1,"edgeAntialiasingMask":251658240,"height":125,"hidden":false,"anchorPoint":{"pointX":0.5,"pointY":0.5}},"layers":[{"animations":[],"layers":[],"texturedRectangle":{"isBackgroundTexture":true,"singleTextureOpacity":1,"textureType":5,"textBaseline":0,"textXHeight":0,"isVerticalText":false},"initialState":{"affineTransform":[1,0,0,1,0,0],"masksToBounds":false,"rotation":0,"scale":1,"position":{"pointX":298.5924072265625,"pointY":60.955718994140625},"width":600,"sublayerTransform":[1,0,0,0,0,1,0,0,0,0,1,0,0,0,0,1],"contentsRect":{"y":0,"x":0,"width":1,"height":1},"opacity":1,"edgeAntialiasingMask":0,"height":125,"hidden":false,"anchorPoint":{"pointX":0.5,"pointY":0.5}},"texture":"1FF09739281378389A7864A2FABF1646"}]}]},{"animations":[],"initialState":{"affineTransform":[1,0,0,1,0,0],"masksToBounds":false,"rotation":0,"scale":1,"position":{"pointX":960,"pointY":540},"width":1920,"sublayerTransform":[1,0,0,0,0,1,0,0,0,0,1,0,0,0,0,1],"contentsRect":{"y":0,"x":0,"width":1,"height":1},"opacity":1,"edgeAntialiasingMask":251658240,"height":1080,"hidden":false,"anchorPoint":{"pointX":0.5,"pointY":0.5}},"layers":[{"animations":[],"initialState":{"affineTransform":[1,0,0,1,0,0],"masksToBounds":false,"rotation":0,"scale":1,"position":{"pointX":708.42601013183594,"pointY":556.29769897460938},"width":1119,"sublayerTransform":[1,0,0,0,0,1,0,0,0,0,1,0,0,0,0,1],"contentsRect":{"y":0,"x":0,"width":1,"height":1},"opacity":1,"edgeAntialiasingMask":251658240,"height":107,"hidden":false,"anchorPoint":{"pointX":0.5,"pointY":0.5}},"objectID":"08632DD1-A4B9-417E-9ACE-10EFF3882177","layers":[{"animations":[],"layers":[],"texturedRectangle":{"isBackgroundTexture":true,"singleTextureOpacity":1,"textureType":5,"textBaseline":0,"textXHeight":0,"isVerticalText":false},"initialState":{"affineTransform":[1,0,0,1,0,0],"masksToBounds":false,"rotation":0,"scale":1,"position":{"pointX":546.57398986816406,"pointY":40.702301025390625},"width":1119,"sublayerTransform":[1,0,0,0,0,1,0,0,0,0,1,0,0,0,0,1],"contentsRect":{"y":0,"x":0,"width":1,"height":1},"opacity":1,"edgeAntialiasingMask":0,"height":107,"hidden":false,"anchorPoint":{"pointX":0.5,"pointY":0.5}},"texture":"234DC0114C5052C599F20172FEC4564C"}]}]},{"animations":[],"initialState":{"affineTransform":[1,0,0,1,0,0],"masksToBounds":false,"rotation":0,"scale":1,"position":{"pointX":960,"pointY":540},"width":1920,"sublayerTransform":[1,0,0,0,0,1,0,0,0,0,1,0,0,0,0,1],"contentsRect":{"y":0,"x":0,"width":1,"height":1},"opacity":1,"edgeAntialiasingMask":251658240,"height":1080,"hidden":false,"anchorPoint":{"pointX":0.5,"pointY":0.5}},"layers":[{"animations":[],"initialState":{"affineTransform":[1,0,0,1,0,0],"masksToBounds":false,"rotation":0,"scale":1,"position":{"pointX":1535.6632080078125,"pointY":569.2515869140625},"width":609,"sublayerTransform":[1,0,0,0,0,1,0,0,0,0,1,0,0,0,0,1],"contentsRect":{"y":0,"x":0,"width":1,"height":1},"opacity":1,"edgeAntialiasingMask":251658240,"height":419,"hidden":false,"anchorPoint":{"pointX":0.5,"pointY":0.5}},"objectID":"D47F1AD5-8832-40FA-80BE-415E49EDE9AD","layers":[{"animations":[],"layers":[],"texturedRectangle":{"isBackgroundTexture":true,"singleTextureOpacity":1,"textureType":5,"textBaseline":0,"textXHeight":0,"isVerticalText":false},"initialState":{"affineTransform":[1,0,0,1,0,0],"masksToBounds":false,"rotation":0,"scale":1,"position":{"pointX":322.3367919921875,"pointY":207.7484130859375},"width":609,"sublayerTransform":[1,0,0,0,0,1,0,0,0,0,1,0,0,0,0,1],"contentsRect":{"y":0,"x":0,"width":1,"height":1},"opacity":1,"edgeAntialiasingMask":0,"height":419,"hidden":false,"anchorPoint":{"pointX":0.5,"pointY":0.5}},"texture":"12B92BA02378E659CCFC9EBD056CFFC8"}]}]},{"animations":[],"initialState":{"affineTransform":[1,0,0,1,0,0],"masksToBounds":false,"rotation":0,"scale":1,"position":{"pointX":960,"pointY":540},"width":1920,"sublayerTransform":[1,0,0,0,0,1,0,0,0,0,1,0,0,0,0,1],"contentsRect":{"y":0,"x":0,"width":1,"height":1},"opacity":1,"edgeAntialiasingMask":251658240,"height":1080,"hidden":false,"anchorPoint":{"pointX":0.5,"pointY":0.5}},"layers":[{"animations":[],"initialState":{"affineTransform":[1,0,0,1,0,0],"masksToBounds":false,"rotation":0,"scale":1,"position":{"pointX":1019.4260101318359,"pointY":996.5687255859375},"width":1739,"sublayerTransform":[1,0,0,0,0,1,0,0,0,0,1,0,0,0,0,1],"contentsRect":{"y":0,"x":0,"width":1,"height":1},"opacity":1,"edgeAntialiasingMask":251658240,"height":247,"hidden":false,"anchorPoint":{"pointX":0.5,"pointY":0.5}},"objectID":"48DFFD9D-57DB-48F9-AE6E-7021ED0DEAA4","layers":[{"animations":[],"layers":[],"texturedRectangle":{"isBackgroundTexture":true,"singleTextureOpacity":1,"textureType":5,"textBaseline":0,"textXHeight":0,"isVerticalText":false},"initialState":{"affineTransform":[1,0,0,1,0,0],"masksToBounds":false,"rotation":0,"scale":1,"position":{"pointX":855.57398986816406,"pointY":55.4312744140625},"width":1739,"sublayerTransform":[1,0,0,0,0,1,0,0,0,0,1,0,0,0,0,1],"contentsRect":{"y":0,"x":0,"width":1,"height":1},"opacity":1,"edgeAntialiasingMask":0,"height":247,"hidden":true,"anchorPoint":{"pointX":0.5,"pointY":0.5}},"texture":"88DA894CD5271F0FBBEEE8AF7E1ED0DA"}]}]}]}},{"effects":[{"beginTime":0,"baseLayer":{"animations":[],"initialState":{"affineTransform":[1,0,0,1,0,0],"masksToBounds":false,"rotation":0,"scale":1,"position":{"pointX":960,"pointY":540},"width":1920,"sublayerTransform":[1,0,0,0,0,1,0,0,0,0,1,0,0,0,0,1],"contentsRect":{"y":0,"x":0,"width":1,"height":1},"opacity":1,"edgeAntialiasingMask":251658240,"height":1080,"hidden":false,"anchorPoint":{"pointX":0.5,"pointY":0.5}},"objectID":"0","layers":[{"animations":[],"initialState":{"affineTransform":[1,0,0,1,0,0],"masksToBounds":false,"rotation":0,"scale":1,"position":{"pointX":960,"pointY":540},"width":1920,"sublayerTransform":[1,0,0,0,0,1,0,0,0,0,1,-0.00035007912466775983,0,0,0,1],"contentsRect":{"y":0,"x":0,"width":1,"height":1},"opacity":1,"edgeAntialiasingMask":251658240,"height":1080,"hidden":false,"anchorPoint":{"pointX":0.5,"pointY":0.5}},"layers":[{"animations":[],"layers":[],"texturedRectangle":{"isBackgroundTexture":false,"singleTextureOpacity":1,"textureType":0,"textBaseline":0,"textXHeight":0,"isVerticalText":false},"initialState":{"affineTransform":[1,0,0,1,0,0],"masksToBounds":false,"rotation":0,"scale":1,"position":{"pointX":960,"pointY":540},"width":1920,"sublayerTransform":[1,0,0,0,0,1,0,0,0,0,1,0,0,0,0,1],"contentsRect":{"y":0,"x":0,"width":1,"height":1},"opacity":1,"edgeAntialiasingMask":0,"height":1080,"hidden":false,"anchorPoint":{"pointX":0.5,"pointY":0.5}},"texture":"594B7529A2D3B69A346AC2757CB9EC71"},{"animations":[{"additive":false,"timeOffset":0,"beginTime":0,"from":{"scalar":false},"repeatCount":0,"fillMode":"both","duration":0.01,"autoreverses":false,"property":"hidden","to":{"scalar":true},"removedOnCompletion":false}],"layers":[],"texturedRectangle":{"isBackgroundTexture":false,"singleTextureOpacity":1,"textureType":0,"textBaseline":0,"textXHeight":0,"isVerticalText":false},"initialState":{"affineTransform":[1,0,0,1,0,0],"masksToBounds":false,"rotation":0,"scale":1,"position":{"pointX":960,"pointY":540},"width":1920,"sublayerTransform":[1,0,0,0,0,1,0,0,0,0,1,0,0,0,0,1],"contentsRect":{"y":0,"x":0,"width":1,"height":1},"opacity":1,"edgeAntialiasingMask":0,"height":1080,"hidden":false,"anchorPoint":{"pointX":0.5,"pointY":0.5}},"texture":"694D88DB94A5EC859458CE1652F311A8"}]}]},"effects":[],"duration":0.01,"type":"transition","attributes":{"direction":0},"name":"none","objectID":"0"}],"automaticPlay":false,"hyperlinks":[],"accessibility":[{"text":"Computing P(x)","targetRectangle":{"y":190.44745779037476,"x":98.599999904632568,"width":403.2600000000001,"height":66.404617309570312}},{"text":"pasted-image.pdf","targetRectangle":{"y":359.92463073134422,"x":1372.4314422607422,"width":484.055419921875,"height":415.23040771484375}},{"text":"The direct way:","targetRectangle":{"y":506.79770004749298,"x":152.92601013183594,"width":399.29999999999995,"height":66.404617309570312}},{"text":"output","targetRectangle":{"y":953.3394775390625,"x":1241.7630462646484,"width":113.45100000000002,"height":44.908004760742301}},{"text":"pasted-image.pdf","targetRectangle":{"y":298.54428100585938,"x":661.4075927734375,"width":597.18487548828125,"height":122.41463470458984}},{"text":"Model-based Information Estimate","targetRectangle":{"y":89,"x":99,"width":1352.0950012159346,"height":100.53440856933594}},{"text":"output","targetRectangle":{"y":685.27264404296864,"x":1261.1632080078125,"width":113.45100000000002,"height":44.908004760742301}},{"text":"pasted-image.pdf","targetRectangle":{"y":521.5151424407959,"x":661.40751647949219,"width":592.26043701171875,"height":73.604621887207031}},{"text":"inputs","targetRectangle":{"y":819.30609512329102,"x":1241.7630462646484,"width":106.9380000000001,"height":44.908004760742301}},{"text":"inputs","targetRectangle":{"y":456.60183306884767,"x":1319.3929481506348,"width":44.908004760742188,"height":106.93799999999999}},{"text":"￼","targetRectangle":{"y":1033.9999701976776,"x":949.49999516521348,"width":20.015999999999963,"height":21.496002197265625}},{"text":"Sampling segment by segment:","targetRectangle":{"y":877.06872665882111,"x":152.92601013183594,"width":826.86999999999989,"height":66.404617309570312}},{"text":"pasted-image.pdf","targetRectangle":{"y":806.94476318359375,"x":1373.2510833740234,"width":500.37890625,"height":243.20823669433594}}],"baseLayer":{"animations":[],"initialState":{"affineTransform":[1,0,0,1,0,0],"masksToBounds":false,"rotation":0,"scale":1,"position":{"pointX":960,"pointY":540},"width":1920,"sublayerTransform":[1,0,0,0,0,1,0,0,0,0,1,0,0,0,0,1],"contentsRect":{"y":0,"x":0,"width":1,"height":1},"opacity":1,"edgeAntialiasingMask":251658240,"height":1080,"hidden":false,"anchorPoint":{"pointX":0.5,"pointY":0.5}},"objectID":"0","layers":[{"animations":[],"initialState":{"affineTransform":[1,0,0,1,0,0],"masksToBounds":false,"rotation":0,"scale":1,"position":{"pointX":960,"pointY":540},"width":1920,"sublayerTransform":[1,0,0,0,0,1,0,0,0,0,1,-0.00035007912466775983,0,0,0,1],"contentsRect":{"y":0,"x":0,"width":1,"height":1},"opacity":1,"edgeAntialiasingMask":251658240,"height":1080,"hidden":false,"anchorPoint":{"pointX":0.5,"pointY":0.5}},"layers":[{"animations":[],"layers":[],"texturedRectangle":{"isBackgroundTexture":false,"singleTextureOpacity":1,"textureType":0,"textBaseline":0,"textXHeight":0,"isVerticalText":false},"initialState":{"affineTransform":[1,0,0,1,0,0],"masksToBounds":false,"rotation":0,"scale":1,"position":{"pointX":960,"pointY":540},"width":1920,"sublayerTransform":[1,0,0,0,0,1,0,0,0,0,1,0,0,0,0,1],"contentsRect":{"y":0,"x":0,"width":1,"height":1},"opacity":1,"edgeAntialiasingMask":0,"height":1080,"hidden":false,"anchorPoint":{"pointX":0.5,"pointY":0.5}},"texture":"694D88DB94A5EC859458CE1652F311A8"}]}]}}]}